README.txt
setup-scripts.py
setup.cfg
lmi/__init__.py
lmi/scripts/__init__.py
lmi/scripts/_metacommand/__init__.py
lmi/scripts/_metacommand/cmdutil.py
lmi/scripts/_metacommand/exit.py
lmi/scripts/_metacommand/help.py
lmi/scripts/_metacommand/interactive.py
lmi/scripts/_metacommand/manager.py
lmi/scripts/_metacommand/toplevel.py
lmi/scripts/_metacommand/util.py
lmi/scripts/common/__init__.py
lmi/scripts/common/configuration.py
lmi/scripts/common/errors.py
lmi/scripts/common/lmi_logging.py
lmi/scripts/common/session.py
lmi/scripts/common/util.py
lmi/scripts/common/command/__init__.py
lmi/scripts/common/command/base.py
lmi/scripts/common/command/checkresult.py
lmi/scripts/common/command/endpoint.py
lmi/scripts/common/command/helper.py
lmi/scripts/common/command/lister.py
lmi/scripts/common/command/meta.py
lmi/scripts/common/command/multiplexer.py
lmi/scripts/common/command/select.py
lmi/scripts/common/command/session.py
lmi/scripts/common/command/show.py
lmi/scripts/common/command/util.py
lmi/scripts/common/formatter/__init__.py
lmi/scripts/common/formatter/command.py
lmi/scripts/common/versioncheck/__init__.py
lmi/scripts/common/versioncheck/parser.py
openlmi_scripts.egg-info/PKG-INFO
openlmi_scripts.egg-info/SOURCES.txt
openlmi_scripts.egg-info/dependency_links.txt
openlmi_scripts.egg-info/entry_points.txt
openlmi_scripts.egg-info/namespace_packages.txt
openlmi_scripts.egg-info/not-zip-safe
openlmi_scripts.egg-info/requires.txt
openlmi_scripts.egg-info/top_level.txt