Metadata-Version: 1.1
Name: openlmi-scripts
Version: 0.4.0
Summary: Client-side library and command-line client
Home-page: http://fedorahosted.org/openlmi/
Author: Michal Minar
Author-email: miminar@redhat.com
License: GPLv2+
Platform: Any
Classifier: License :: OSI Approved :: GNU General Public License v2 or later (GPLv2+)
Classifier: Operating System :: POSIX :: Linux
Classifier: Topic :: System :: Systems Administration
Classifier: Programming Language :: Python
Classifier: Programming Language :: Python :: 2
Classifier: Programming Language :: Python :: 2.7
Classifier: Intended Audience :: Developers
Classifier: Environment :: Console
